utilities/__init__.py
utilities/log_util.py
vivilib-0.0.1.dist-info/METADATA
vivilib-0.0.1.dist-info/WHEEL
vivilib-0.0.1.dist-info/top_level.txt
vivilib-0.0.1.dist-info/RECORD
