Metadata-Version: 2.1
Name: vivilib
Version: 0.0.1
Summary: vivilib test release
Author: Vivian Wang
Author-email: lilcatriag@gmail.com
Keywords: python,vivilib
Classifier: Development Status :: 3 - Alpha
Classifier: Intended Audience :: Education
Classifier: Programming Language :: Python :: 2
Classifier: Programming Language :: Python :: 3
Classifier: Operating System :: MacOS :: MacOS X
Classifier: Operating System :: Microsoft :: Windows
